locale_lint/__init__.py
locale_lint/cli.py
locale_lint/test_cli.py
locale_lint-0.3.1.dist-info/licenses/LICENSE
locale_lint-0.3.1.dist-info/METADATA
locale_lint-0.3.1.dist-info/WHEEL
locale_lint-0.3.1.dist-info/entry_points.txt
locale_lint-0.3.1.dist-info/top_level.txt
locale_lint-0.3.1.dist-info/RECORD
