Metadata-Version: 2.4
Name: locale_lint
Version: 0.3.1
Summary: Weblate Locale Linter
Author-email: Michal Čihař <michal@cihar.com>
License-Expression: GPL-3.0-or-later
Project-URL: Documentation, https://docs.weblate.org/
Project-URL: Download, https://github.com/WeblateOrg/locale_lint
Project-URL: Funding, https://weblate.org/donate/
Project-URL: Homepage, https://weblate.org/
Project-URL: Issue Tracker, https://github.com/WeblateOrg/locale_lint/issues
Project-URL: Source Code, https://github.com/WeblateOrg/locale_lint
Project-URL: Twitter, https://twitter.com/WeblateOrg
Keywords: i18n l10n gettext git mercurial translate
Platform: any
Classifier: Development Status :: 5 - Production/Stable
Classifier: Intended Audience :: Developers
Classifier: Operating System :: OS Independent
Classifier: Programming Language :: Python
Classifier: Programming Language :: Python :: 3
Classifier: Programming Language :: Python :: 3 :: Only
Classifier: Programming Language :: Python :: 3.9
Classifier: Programming Language :: Python :: 3.10
Classifier: Programming Language :: Python :: 3.11
Classifier: Programming Language :: Python :: 3.12
Classifier: Programming Language :: Python :: 3.13
Classifier: Topic :: Software Development :: Internationalization
Classifier: Topic :: Software Development :: Localization
Classifier: Topic :: Utilities
Requires-Python: >=3.9
License-File: LICENSE
Requires-Dist: click<9.0,>=8.0
Requires-Dist: translate-toolkit<3.16.0,>=3.5.1
Requires-Dist: translation-finder<3.0,>=2.11
Provides-Extra: lint
Requires-Dist: pre-commit==4.2.0; extra == "lint"
Provides-Extra: test
Requires-Dist: pytest; extra == "test"
Requires-Dist: pytest-cov; extra == "test"
Dynamic: license-file
